res2df/__init__.py
res2df/__version__.py
res2df/common.py
res2df/compdat.py
res2df/constants.py
res2df/csv2res.py
res2df/equil.py
res2df/faults.py
res2df/fipreports.py
res2df/grid.py
res2df/gruptree.py
res2df/inferdims.py
res2df/nnc.py
res2df/parameters.py
res2df/pillars.py
res2df/pvt.py
res2df/py.typed
res2df/res2csv.py
res2df/res2csvlogger.py
res2df/resdatafiles.py
res2df/rft.py
res2df/satfunc.py
res2df/summary.py
res2df/svg_color_keyword_names.txt
res2df/trans.py
res2df/version.py
res2df/wcon.py
res2df/wellcompletiondata.py
res2df/wellconnstatus.py
res2df/hook_implementations/__init__.py
res2df/hook_implementations/forward_model_steps.py
res2df/opmkeywords/BRANPROP
res2df/opmkeywords/COMPDAT
res2df/opmkeywords/COMPLUMP
res2df/opmkeywords/COMPSEGS
res2df/opmkeywords/DENSITY
res2df/opmkeywords/EQLDIMS
res2df/opmkeywords/EQUIL
res2df/opmkeywords/FAULTS
res2df/opmkeywords/GRUPNET
res2df/opmkeywords/GRUPTREE
res2df/opmkeywords/NODEPROP
res2df/opmkeywords/PBVD
res2df/opmkeywords/PDVD
res2df/opmkeywords/PVDG
res2df/opmkeywords/PVDO
res2df/opmkeywords/PVTG
res2df/opmkeywords/PVTO
res2df/opmkeywords/PVTW
res2df/opmkeywords/ROCK
res2df/opmkeywords/RSVD
res2df/opmkeywords/RVVD
res2df/opmkeywords/SGFN
res2df/opmkeywords/SGOF
res2df/opmkeywords/SGWFN
res2df/opmkeywords/SLGOF
res2df/opmkeywords/SOF2
res2df/opmkeywords/SOF3
res2df/opmkeywords/SWFN
res2df/opmkeywords/SWOF
res2df/opmkeywords/TABDIMS
res2df/opmkeywords/VFPINJ
res2df/opmkeywords/VFPPROD
res2df/opmkeywords/WCONHIST
res2df/opmkeywords/WCONINJE
res2df/opmkeywords/WCONINJH
res2df/opmkeywords/WCONPROD
res2df/opmkeywords/WELOPEN
res2df/opmkeywords/WELSEGS
res2df/opmkeywords/WELSPECS
res2df/opmkeywords/WLIST
res2df/opmkeywords/WSEGAICD
res2df/opmkeywords/WSEGSICD
res2df/opmkeywords/WSEGVALV
res2df/opmkeywords/__init__.py
res2df/opmkeywords/readme
res2df/opmkeywords/runmetoupdate.sh
res2df/vfp/__init__.py
res2df/vfp/_vfp.py
res2df/vfp/_vfpcommon.py
res2df/vfp/_vfpdefs.py
res2df/vfp/_vfpinj.py
res2df/vfp/_vfpprod.py
res2df-1.3.11.dist-info/licenses/LICENSE
res2df-1.3.11.dist-info/METADATA
res2df-1.3.11.dist-info/WHEEL
res2df-1.3.11.dist-info/entry_points.txt
res2df-1.3.11.dist-info/top_level.txt
res2df-1.3.11.dist-info/RECORD
