Metadata-Version: 2.4
Name: res2df
Version: 1.3.11
Summary: Convert reservoir simulator input and output to DataFrames
Author-email: Håvard Berland <havb@equinor.com>
License-Expression: GPL-3.0-only
Project-URL: Homepage, https://github.com/equinor/res2df
Project-URL: Repository, https://github.com/equinor/res2df
Project-URL: Documentation, https://equinor.github.io/res2df/
Keywords: energy,subsurface,reservoir,scientific,engineering
Classifier: Development Status :: 5 - Production/Stable
Classifier: Intended Audience :: Science/Research
Classifier: Topic :: Scientific/Engineering
Classifier: Topic :: Software Development :: Libraries
Classifier: Topic :: Utilities
Classifier: Programming Language :: Python :: 3.11
Classifier: Programming Language :: Python :: 3.12
Classifier: Programming Language :: Python :: 3.13
Classifier: Programming Language :: Python :: 3.14
Classifier: Natural Language :: English
Requires-Python: >=3.11
License-File: LICENSE
Requires-Dist: resdata>=5.0.0-b0
Requires-Dist: resfo
Requires-Dist: networkx
Requires-Dist: numpy
Requires-Dist: opm>=2020.10.2
Requires-Dist: pandas
Requires-Dist: pyarrow
Requires-Dist: pyyaml>=5.1
Requires-Dist: treelib
Provides-Extra: tests
Requires-Dist: pytest; extra == "tests"
Requires-Dist: pytest-cov; extra == "tests"
Requires-Dist: pytest-mock; extra == "tests"
Requires-Dist: pytest-timeout; extra == "tests"
Provides-Extra: style
Requires-Dist: pre-commit; extra == "style"
Provides-Extra: types
Requires-Dist: mypy; extra == "types"
Requires-Dist: types-PyYAML; extra == "types"
Requires-Dist: types-python-dateutil; extra == "types"
Requires-Dist: types-setuptools; extra == "types"
Requires-Dist: types-networkx; extra == "types"
Requires-Dist: pandas-stubs; extra == "types"
Provides-Extra: docs
Requires-Dist: sphinx-autoapi; extra == "docs"
Requires-Dist: ipython; extra == "docs"
Requires-Dist: rstcheck; extra == "docs"
Requires-Dist: setuptools; extra == "docs"
Requires-Dist: sphinx<9; extra == "docs"
Requires-Dist: sphinx-argparse; extra == "docs"
Requires-Dist: sphinx-autodoc-typehints; extra == "docs"
Requires-Dist: sphinx_rtd_theme>=3.1.0.rc1; extra == "docs"
Provides-Extra: ert
Requires-Dist: ert>=10.2.0b13; extra == "ert"
Dynamic: license-file
